{
  "categorias": [
    {
      "titulo": "Power Black",
      "link": "https://movimentoblackmoney.com.br/",
      "cor": "#6BD1FF",
      "link_extra": {
        "text": "Negros no Controle",
        "url": ""
      },
      "videos": [
        {
          "titulo": "Daniel Caesar - Best Part",
          "url": "https://www.youtube.com/watch?v=R1yqJisehhQ"
        },
        {
          "titulo": "Nina Silva e o Movimento Black Money",
          "url": "https://www.youtube.com/watch?v=mR_BghDLg4c"
        },
        {
          "titulo": "#tbt AFROPYTHON CONF | 1ª edição | Porto Alegre | 2019",
          "url": "https://www.youtube.com/watch?v=UL0wCfVviD4"
        },
        {
          "titulo": "Rodrigo Ribeiro- BrazilJS Conf 2019",
          "url": "https://www.youtube.com/watch?v=C81ftRbSj8M"
        },
        {
          "titulo": "TECNOLOGIA E CULTURA NEGRA | Mentes da Tecnologia S01E05 - Nina Silva",
          "url": "https://www.youtube.com/watch?v=lABz-0PRX5k"
        },
        {
          "titulo": "RACISMO na TECNOLOGIA - Papo de Preta",
          "url": "https://www.youtube.com/watch?v=cAh_NlhAnYE"
        },
        {
          "titulo": "Ninguém nasce racista. Continue Criança.",
          "url": "https://www.youtube.com/watch?v=qmYucZKoxQA"
        },
        {
          "titulo": "A mulata que nunca chegou",
          "url": "https://www.youtube.com/watch?v=02TBfKeBbRw"
        }        
      ]
    },
    {
      "titulo": "Happy with she",
      "cor": "#00C86F",
      "link_extra": {
        "text": "Feliz com ela",
        "url": "https://www.alura.com.br/cursos-online-programacao"
      },
      "videos": [
        {
          "titulo": "Best of Black Couples Couple goals on TikTok Compilation",
          "url": "https://www.youtube.com/watch?v=HAJ83qAKP_M"
        },
        {
          "titulo": "BLACK COUPLES COMPILATION",
          "url": "https://www.youtube.com/watch?v=uliHT2VXhdI"
        },
        {
          "titulo": "Angelo&DeLise Performance Native Detroiter Black Affair",
          "url": "https://www.youtube.com/watch?v=YfGZAYSqufg"
        },
        {
          "titulo": "Denatora & Machoc Best Couple Dance Videos Compilation | Relationship Goals",
          "url": "https://www.youtube.com/watch?v=tIAY3MYywD0"
        }, 
        {
          "titulo": "Mr. Killa - Oil it |Choreography by Wendell Bullen & Royal G",
          "url": "https://www.youtube.com/watch?v=1j3RY3_CpG8"
        }
      ]
    },
    {
      "titulo": "Black lives matter",
      "cor": "#9cd33b",
      "link_extra": {
        "text": "Vidas Negras Importam !!!",
        "url": ""
      },
      "videos": [
        {
          "titulo": "Dax - BLACK LIVES MATTER (Official Music Video)",
          "url": "https://www.youtube.com/watch?v=A2o15RCtSS0"
        },
        {
          "titulo": "Dax - Dear God (Official Music Video)",
          "url": "https://www.youtube.com/watch?v=nzCIeNhw8oE"
        },
        {
          "titulo": "Black Lives Matter Protests Around the World",
          "url": "https://www.youtube.com/watch?v=4Vl4I0weXPU"
        },
        {
          "titulo": "Dae Dae - Black Lives Matter ft. London on Da Track (Official Lyric Video)",
          "url": "https://www.youtube.com/watch?v=y8hb-eGKiUQ"
        }
      ]
    },
    {
      "titulo": "Filmes",
      "cor": "orange",
      "videos": [
        {
          "titulo": "The Rise of Black Lives Matter | VPRO documentary | 2016",
          "url": "https://www.youtube.com/watch?v=tgFI0phqRIY"
        },
        {
          "titulo": "Por que dizemos Vidas Negras Importam | Michael Che Matters | Netflix Brasi",
          "url": "https://www.youtube.com/watch?v=aQpJF9t-zJ4"
        },
        {
          "titulo": "Morte No Funeral - Trailer",
          "url": "https://www.youtube.com/watch?v=iNhFHbeZxHI"
        },
        {
          "titulo": "O Bom Filho À Casa Torna 2008 Trailer Original",
          "url": "https://www.youtube.com/watch?v=Q-aYehf_cAI"
        }
      ]
    },
    {
      "titulo": "Couple Black",
      "cor": "red",
      "link_extra": {
        "text": "Casal negro",
        "url": "https://www.youtube.com/watch?v=Goo4Vcb5S74"
      },
      "videos": [
        {
          "titulo": "Casais Negros Perfeitos Tumbrl",
          "url": "https://www.youtube.com/watch?v=k8N3D_YHZa8"
        },
        {
          "titulo": "Casal negro tumblr❤💑 Black Couple Tumblr",
          "url": "https://www.youtube.com/watch?v=m8OMWfNNsTo"
        },
        {
          "titulo": "casais negros",
          "url": "https://www.youtube.com/watch?v=_SjqnVex3Cg"
        },
        {
          "titulo": "CASAIS NEGROS",
          "url": "https://www.youtube.com/watch?v=euCHad-h-c4"
        },
        {
          "titulo": "Casais negros perfeitos Tumblr/ namorados apaixonados (essa música é foda)",
          "url": "https://www.youtube.com/watch?v=n1FkfDCTtyQ"
        }
      ]
    },
    {
      "titulo": "Fogo nos Racistas",
      "cor": "#6b5be2",
      "link_extra": {
        "text": "Revolução Negra",
        "url": "https://alura.com.br/curso-online-aprender-a-aprender-tecnicas-para-seu-autodesenvolvimento"
      },
      "videos": [
        {
          "titulo": "Djonga - Olho de Tigre",
          "url": "https://www.youtube.com/watch?v=0D84LFKiGbo"
        },
        {
          "titulo": "Emicida fala sobre a desigualdade e racismo no Programa Altas Horas",
          "url": "https://www.youtube.com/watch?v=x1AA-37rjsc"
        },
        {
          "titulo": "Tawane Theodoro | Fogo nos racistas | Final Slam da Guilhermina",
          "url": "https://www.youtube.com/watch?v=gq9aL64yoI4"
        },
        {
          "titulo": "8 relatos sobre como é ser negro no Brasil",
          "url": "https://www.youtube.com/watch?v=fl6tvDlTJbg"
        },
        {
          "titulo": "O emocionado discurso da menina de 9 anos que chamou a atenção do mundo para a tensão racial nos EUA",
          "url": "https://www.youtube.com/watch?v=Wf7rXkE9Jkc"
        }
      ]
    }
  ]
}